genius-trending.py
genius_trending.py
genius_trending.py-1.0.0.2.dist-info/METADATA
genius_trending.py-1.0.0.2.dist-info/RECORD
genius_trending.py-1.0.0.2.dist-info/WHEEL
genius_trending.py-1.0.0.2.dist-info/top_level.txt
